__init__.py
fitters.cpython-312-x86_64-linux-gnu.so
parameterset.cpython-312-x86_64-linux-gnu.so
pydp3.cpython-312-x86_64-linux-gnu.so
DP3.libs/aoflagger/strategies/aartfaac-default.lua
DP3.libs/aoflagger/strategies/apertif-2020-02-26-with-autocorrelations.lua
DP3.libs/aoflagger/strategies/apertif-2020-05-19.lua
DP3.libs/aoflagger/strategies/apertif-2021-02-14.lua
DP3.libs/aoflagger/strategies/apertif-2021-03-09.lua
DP3.libs/aoflagger/strategies/apertif-default.lua
DP3.libs/aoflagger/strategies/arecibo-default.lua
DP3.libs/aoflagger/strategies/atca-default.lua
DP3.libs/aoflagger/strategies/atca-l-band.lua
DP3.libs/aoflagger/strategies/bighorns-default.lua
DP3.libs/aoflagger/strategies/generic-default.lua
DP3.libs/aoflagger/strategies/generic-minimal.lua
DP3.libs/aoflagger/strategies/jvla-default.lua
DP3.libs/aoflagger/strategies/lofar-beamformed.lua
DP3.libs/aoflagger/strategies/lofar-default.lua
DP3.libs/aoflagger/strategies/lofar-hba-wideband.lua
DP3.libs/aoflagger/strategies/lofar-lba-wideband.lua
DP3.libs/aoflagger/strategies/mwa-default.lua
DP3.libs/aoflagger/strategies/nenufar-default.lua
DP3.libs/aoflagger/strategies/parkes-default.lua
DP3.libs/aoflagger/strategies/wsrt-default.lua
dp3/__init__.py
dp3/fitters.cpython-312-x86_64-linux-gnu.so
dp3/parameterset.cpython-312-x86_64-linux-gnu.so
dp3/pydp3.cpython-312-x86_64-linux-gnu.so
dp3/steps/__init__.py
dp3/steps/queue.py
dp3.libs/libDP3-69355248.so
dp3.libs/libaoflagger-da0ad116.so.0
dp3.libs/libblas-357956a1.so.3.4.2
dp3.libs/libboost_atomic-1419dacb.so.1.85.0
dp3.libs/libboost_date_time-5389eb85.so.1.85.0
dp3.libs/libboost_filesystem-a429b93a.so.1.85.0
dp3.libs/libboost_program_options-396ce058.so.1.85.0
dp3.libs/libboost_system-af05c183.so.1.85.0
dp3.libs/libcasa_casa-e569dfdc.so.8
dp3.libs/libcasa_fits-5520a1ac.so.8
dp3.libs/libcasa_measures-30f40909.so.8
dp3.libs/libcasa_ms-c057626f.so.8
dp3.libs/libcasa_scimath-7aa12d4b.so.8
dp3-6.5.1.dist-info/METADATA
dp3-6.5.1.dist-info/WHEEL
dp3-6.5.1.dist-info/entry_points.txt
dp3-6.5.1.dist-info/top_level.txt
dp3-6.5.1.dist-info/RECORD
dp3-6.5.1.dist-info/licenses/LICENSE
