Metadata-Version: 2.4
Name: dp3
Version: 6.5.1
Summary: DP3
Home-page: https://dp3.readthedocs.io/
Author: ASTRON
Author-email: dijkema@astron.nl
Classifier: Development Status :: 5 - Production/Stable
Classifier: License :: OSI Approved :: GNU General Public License v3 (GPLv3)
Classifier: Topic :: Scientific/Engineering :: Astronomy
Requires-Python: >=3.8
License-File: LICENSE
Dynamic: author
Dynamic: author-email
Dynamic: classifier
Dynamic: description
Dynamic: home-page
Dynamic: license-file
Dynamic: requires-python
Dynamic: summary
